mst_package/__init__.py
mst_package/module.py
mst_package-0.1.1.dist-info/METADATA
mst_package-0.1.1.dist-info/WHEEL
mst_package-0.1.1.dist-info/RECORD
