Metadata-Version: 2.1
Name: mst-package
Version: 0.1.1
Summary: 
Author: Stelmacheris
Author-email: stelmokas00@gmail.com
Requires-Python: >=3.12,<4.0
Classifier: Programming Language :: Python :: 3
Classifier: Programming Language :: Python :: 3.12
Requires-Dist: numpy (>=2.0.1,<3.0.0)
